{
    "created": "2025-01-28 12:59:15",
    "lines": [
        {
            "currencyTypeName": "Divine Orb",
            "pay": {
                "id": 0,
                "league_id": 232,
                "pay_currency_id": 3,
                "get_currency_id": 1,
                "sample_time_utc": "2025-01-28T19:14:47.9662592Z",
                "count": 150,
                "value": 0.00588,
                "data_point_count": 1,
                "includes_secondary": false,
                "listing_count": 3444
            },
            "receive": {
                "id": 0,
                "league_id": 232,
                "pay_currency_id": 1,
                "get_currency_id": 3,
                "sample_time_utc": "2025-01-28T19:14:47.9662592Z",
                "count": 50,
                "value": 171.42857,
                "data_point_count": 1,
                "includes_secondary": false,
                "listing_count": 744
            },
            "chaosEquivalent": 170.41,
            "detailsId": "divine-orb"
        }
    ],
    "currencyDetails": [
        {
            "id": 1,
            "icon": "https://web.poecdn.com/gen/image/WzI1LDE0LHsiZiI6IjJESXRlbXMvQ3VycmVuY3kvQ3VycmVuY3lSZXJvbGxSYXJlIiwidyI6MSwiaCI6MSwic2NhbGUiOjF9XQ/d119a0d734/CurrencyRerollRare.png",
            "name": "Chaos Orb",
            "tradeId": "chaos"
        },
        {
            "id": 2,
            "icon": "https://web.poecdn.com/gen/image/WzI1LDE0LHsiZiI6IjJESXRlbXMvQ3VycmVuY3kvQ3VycmVuY3lBZGRNb2RUb1JhcmUiLCJ3IjoxLCJoIjoxLCJzY2FsZSI6MX1d/b102771c23/CurrencyAddModToRare.png",
            "name": "Exalted Orb",
            "tradeId": "exalted"
        },
        {
            "id": 3,
            "icon": "https://web.poecdn.com/gen/image/WzI1LDE0LHsiZiI6IjJESXRlbXMvQ3VycmVuY3kvQ3VycmVuY3lNb2RWYWx1ZXMiLCJ3IjoxLCJoIjoxLCJzY2FsZSI6MX1d/e1a54ff97d/CurrencyModValues.png",
            "name": "Divine Orb",
            "tradeId": "divine"
        }
    ]
}